docs/DirectionalLight_example.py
docs/Entity_look_at_2d_example.py
docs/documentation_generator.py
docs/documentation_parser.py
docs/mouse_example_getting_mouse_position_in_3d.py
docs/platformer_tutorial.py
docs/tutorial_generator.py
samples/3d_level_editor_old.py
samples/_run_all_samples.py
samples/after_decorator_example.py
samples/angle_lerping.py
samples/bullet_hell.py
samples/cheap_physics.py
samples/clicker_game.py
samples/column_graph.py
samples/digging_game.py
samples/entity_demo.py
samples/example_game.py
samples/fps.py
samples/grass_fields.py
samples/heightmap_editor.py
samples/inventory.py
samples/loading_screen.py
samples/look_at_test.py
samples/main_menu.py
samples/main_menu_simple.py
samples/minecraft_clone.py
samples/monkey_ball.py
samples/move_along_path.py
samples/pause_menu.py
samples/pixel_perfect.py
samples/platformer.py
samples/pong.py
samples/roguelike.py
samples/rubiks_cube.py
samples/slow_motion.py
samples/small_example_game.py
samples/terrain_mesh.py
samples/terraria_clone.py
samples/tic_tac_toe.py
samples/trigger_box.py
samples/undo.py
samples/volumetric_cube.py
samples/world_grid.py
samples/networking/club_bear.py
samples/networking/hello_world.py
samples/networking/hello_world_rpc.py
samples/networking/host_authoritative.py
samples/networking/shared_object.py
samples/settings_file_example/settings_example.py
samples/settings_file_example/ursina_settings.py
tests/test_load_blender_model/test_load_blender_model.py
ursina/__init__.py
ursina/application.py
ursina/array_tools.py
ursina/audio.py
ursina/boxcast.py
ursina/build.py
ursina/camera.py
ursina/collider.py
ursina/color.py
ursina/curve.py
ursina/destroy.py
ursina/duplicate.py
ursina/entity.py
ursina/gamepad.py
ursina/hit_info.py
ursina/input_handler.py
ursina/lights.py
ursina/main.py
ursina/mesh.py
ursina/mesh_exporter.py
ursina/mesh_importer.py
ursina/mouse.py
ursina/music_system.py
ursina/networking.py
ursina/physics.py
ursina/raycast.py
ursina/scene.py
ursina/sequence.py
ursina-8.1.1.dist-info/licenses/LICENSE
ursina-8.1.1.dist-info/METADATA
ursina-8.1.1.dist-info/WHEEL
ursina-8.1.1.dist-info/top_level.txt
ursina-8.1.1.dist-info/RECORD
