Metadata-Version: 2.4
Name: ursina
Version: 8.1.1
Summary: An easy to use game engine/framework for python.
Author-email: Petter Amland <pokepetter@gmail.com>
License: MIT
Project-URL: homepage, https://github.com/pokepetter/ursina
Keywords: game development
Requires-Python: >=3.12
License-File: LICENSE
Requires-Dist: panda3d>=1.10.15
Requires-Dist: panda3d-gltf>=1.3.0
Requires-Dist: pillow>=10.0.0
Requires-Dist: pyperclip>=1.9.0
Requires-Dist: screeninfo>=0.8.1
Requires-Dist: sswg==4.3.0
Provides-Extra: extra
Requires-Dist: imageio>=2.37.0; extra == "extra"
Requires-Dist: numpy>=2.3.1; extra == "extra"
Requires-Dist: psutil>=7.0.0; extra == "extra"
Requires-Dist: thumbhash-python>=1.0.1; extra == "extra"
Requires-Dist: tripy>=1.0.0; extra == "extra"
Dynamic: license-file
